devops_toolset/.devops/coverage-report.css
devops_toolset/.devops/pipeline-build-devopstoolset-ci.yml
devops_toolset/.devops/pipeline-template-artifacts.yml
devops_toolset/.devops/pipeline-template-i18n-xgettext.yml
devops_toolset/.devops/pipeline-template-i18n.yml
devops_toolset/.devops/pipeline-template-intellicode.yml
devops_toolset/.devops/pipeline-template-project-info.yml
devops_toolset/.devops/pipeline-template-python-setup.yml
devops_toolset/.devops/pipeline-template-sonarcloud.yml
devops_toolset/.devops/pipeline-template-unit-tests.yml
devops_toolset/.devops/scripts/install-dependencies.sh
devops_toolset/.devops/sonar-project.properties
devops_toolset/.pylintrc
devops_toolset/__init__.py
devops_toolset/configure.py
devops_toolset/core/__init__.py
devops_toolset/core/app.py
devops_toolset/core/ColorFormatter.py
devops_toolset/core/CommandsCore.py
devops_toolset/core/LiteralsCore.py
devops_toolset/core/log_setup.py
devops_toolset/core/log_tools.py
devops_toolset/core/settings.py
devops_toolset/core/ValueDictsBase.py
devops_toolset/devops_platforms/__init__.py
devops_toolset/devops_platforms/aws/__init__.py
devops_toolset/devops_platforms/aws/environment.py
devops_toolset/devops_platforms/aws/Literals.py
devops_toolset/devops_platforms/azuredevops/__init__.py
devops_toolset/devops_platforms/azuredevops/cli.py
devops_toolset/devops_platforms/azuredevops/commands.py
devops_toolset/devops_platforms/azuredevops/environment.py
devops_toolset/devops_platforms/azuredevops/Literals.py
devops_toolset/devops_platforms/azuredevops/restapi.py
devops_toolset/devops_platforms/commands.py
devops_toolset/devops_platforms/common.py
devops_toolset/devops_platforms/constants.py
devops_toolset/devops_platforms/Literals.py
devops_toolset/devops_platforms/README.md
devops_toolset/devops_platforms/sonarx.py
devops_toolset/filesystem/__init__.py
devops_toolset/filesystem/constants.py
devops_toolset/filesystem/Literals.py
devops_toolset/filesystem/parsers.py
devops_toolset-2.17.7.dist-info/LICENSE
devops_toolset-2.17.7.dist-info/METADATA
devops_toolset-2.17.7.dist-info/WHEEL
devops_toolset-2.17.7.dist-info/RECORD
