Metadata-Version: 2.3
Name: devops-toolset
Version: 2.17.7
Summary: General purpose DevOps-related scripts and tools
License: MIT
Author: Alberto Carbonell
Author-email: alberto.carbonell@aheadlabs.com
Requires-Python: >=3.9
Classifier: License :: OSI Approved :: MIT License
Classifier: Programming Language :: Python :: 3
Classifier: Programming Language :: Python :: 3.9
Classifier: Programming Language :: Python :: 3.10
Classifier: Programming Language :: Python :: 3.11
Classifier: Programming Language :: Python :: 3.12
Classifier: Programming Language :: Python :: 3.13
Requires-Dist: boto3 (>=1.36.13,<2.0.0)
Requires-Dist: botocore (>=1.36.13,<2.0.0)
Requires-Dist: clint (>=0.5.1,<0.6.0)
Requires-Dist: colorama (>=0.4.6,<0.5.0)
Requires-Dist: pendulum (>=3.0.0,<4.0.0)
Requires-Dist: pyfiglet (>=1.0.2,<2.0.0)
Requires-Dist: pytest (>=8.3.4,<9.0.0)
Requires-Dist: pytest-cov (>=6.0.0,<7.0.0)
Requires-Dist: pyyaml (>=6.0.2,<7.0.0)
Requires-Dist: requests (>=2.32.3,<3.0.0)
Requires-Dist: setuptools (>=75.8.0,<76.0.0)
Project-URL: Bug Tracker, https://github.com/aheadlabs/devops-toolset/issues
Project-URL: Documentation, https://github.com/aheadlabs/devops-toolset/docs/
Project-URL: Homepage, https://aheadlabs.com/
Project-URL: Repository, https://github.com/aheadlabs/devops-toolset
